{
  "version": 1,
  "videoId": "M8zvnBXGeVk",
  "meta": {
    "track": "君のいちばんになりたい",
    "artist": "胡桃のあ",
    "generatedAt": "2025-12-13T14:21:22.578583Z"
  },
  "lines": [
    {
      "index": 0,
      "text": "いちばんになりたい",
      "startTimeMs": 2023,
      "endTimeMs": 4413,
      "chars": [
        {
          "i": 0,
          "c": "い",
          "t": 2023
        },
        {
          "i": 1,
          "c": "ち",
          "t": 2315
        },
        {
          "i": 2,
          "c": "ば",
          "t": 2591
        },
        {
          "i": 3,
          "c": "ん",
          "t": 2776
        },
        {
          "i": 4,
          "c": "に",
          "t": 3364
        },
        {
          "i": 5,
          "c": "な",
          "t": 3552
        },
        {
          "i": 6,
          "c": "り",
          "t": 3723
        },
        {
          "i": 7,
          "c": "た",
          "t": 4006
        },
        {
          "i": 8,
          "c": "い",
          "t": 4413
        }
      ]
    },
    {
      "index": 1,
      "text": "まだ小さなヒカリ",
      "startTimeMs": 4891,
      "endTimeMs": 7859,
      "chars": [
        {
          "i": 0,
          "c": "ま",
          "t": 4891
        },
        {
          "i": 1,
          "c": "だ",
          "t": 5551
        },
        {
          "i": 2,
          "c": "小",
          "t": 5984
        },
        {
          "i": 3,
          "c": "さ",
          "t": 6168
        },
        {
          "i": 4,
          "c": "な",
          "t": 6374
        },
        {
          "i": 5,
          "c": "ヒ",
          "t": 6789
        },
        {
          "i": 6,
          "c": "カ",
          "t": 7190
        },
        {
          "i": 7,
          "c": "リ",
          "t": 7859
        }
      ]
    },
    {
      "index": 2,
      "text": "こんな僕だけど",
      "startTimeMs": 8084,
      "endTimeMs": 11153,
      "chars": [
        {
          "i": 0,
          "c": "こ",
          "t": 8084
        },
        {
          "i": 1,
          "c": "ん",
          "t": 8325
        },
        {
          "i": 2,
          "c": "な",
          "t": 8826
        },
        {
          "i": 3,
          "c": "僕",
          "t": 9547
        },
        {
          "i": 4,
          "c": "だ",
          "t": 9944
        },
        {
          "i": 5,
          "c": "け",
          "t": 10315
        },
        {
          "i": 6,
          "c": "ど",
          "t": 11153
        }
      ]
    },
    {
      "index": 3,
      "text": "愛してほしいのです",
      "startTimeMs": 11672,
      "endTimeMs": 26722,
      "chars": [
        {
          "i": 0,
          "c": "愛",
          "t": 11672
        },
        {
          "i": 1,
          "c": "し",
          "t": 11965
        },
        {
          "i": 2,
          "c": "て",
          "t": 13452
        },
        {
          "i": 3,
          "c": "ほ",
          "t": 13630
        },
        {
          "i": 4,
          "c": "し",
          "t": 13825
        },
        {
          "i": 5,
          "c": "い",
          "t": 14224
        },
        {
          "i": 6,
          "c": "の",
          "t": 14665
        },
        {
          "i": 7,
          "c": "で",
          "t": 15105
        },
        {
          "i": 8,
          "c": "す",
          "t": 26722
        }
      ]
    },
    {
      "index": 4,
      "text": "自信ありげなフリして",
      "startTimeMs": 27897,
      "endTimeMs": 30420,
      "chars": [
        {
          "i": 0,
          "c": "自",
          "t": 27897
        },
        {
          "i": 1,
          "c": "信",
          "t": 28404
        },
        {
          "i": 2,
          "c": "あ",
          "t": 28817
        },
        {
          "i": 3,
          "c": "り",
          "t": 28996
        },
        {
          "i": 4,
          "c": "げ",
          "t": 29377
        },
        {
          "i": 5,
          "c": "な",
          "t": 29594
        },
        {
          "i": 6,
          "c": "フ",
          "t": 29771
        },
        {
          "i": 7,
          "c": "リ",
          "t": 29933
        },
        {
          "i": 8,
          "c": "し",
          "t": 30112
        },
        {
          "i": 9,
          "c": "て",
          "t": 30420
        }
      ]
    },
    {
      "index": 5,
      "text": "ホントは精一杯な",
      "startTimeMs": 30700,
      "endTimeMs": 32949,
      "chars": [
        {
          "i": 0,
          "c": "ホ",
          "t": 30700
        },
        {
          "i": 1,
          "c": "ン",
          "t": 30869
        },
        {
          "i": 2,
          "c": "ト",
          "t": 31206
        },
        {
          "i": 3,
          "c": "は",
          "t": 31447
        },
        {
          "i": 4,
          "c": "精",
          "t": 31600
        },
        {
          "i": 5,
          "c": "一",
          "t": 31798
        },
        {
          "i": 6,
          "c": "杯",
          "t": 32205
        },
        {
          "i": 7,
          "c": "な",
          "t": 32949
        }
      ]
    },
    {
      "index": 6,
      "text": "等身大の女の子です",
      "startTimeMs": 33395,
      "endTimeMs": 38350,
      "chars": [
        {
          "i": 0,
          "c": "等",
          "t": 33395
        },
        {
          "i": 1,
          "c": "身",
          "t": 33993
        },
        {
          "i": 2,
          "c": "大",
          "t": 34911
        },
        {
          "i": 3,
          "c": "の",
          "t": 35355
        },
        {
          "i": 4,
          "c": "女",
          "t": 36366
        },
        {
          "i": 5,
          "c": "の",
          "t": 36724
        },
        {
          "i": 6,
          "c": "子",
          "t": 37091
        },
        {
          "i": 7,
          "c": "で",
          "t": 37591
        },
        {
          "i": 8,
          "c": "す",
          "t": 38350
        }
      ]
    },
    {
      "index": 7,
      "text": "どんな仕草や言葉が",
      "startTimeMs": 38863,
      "endTimeMs": 40888,
      "chars": [
        {
          "i": 0,
          "c": "ど",
          "t": 38863
        },
        {
          "i": 1,
          "c": "ん",
          "t": 39041
        },
        {
          "i": 2,
          "c": "な",
          "t": 39462
        },
        {
          "i": 3,
          "c": "仕",
          "t": 39768
        },
        {
          "i": 4,
          "c": "草",
          "t": 40047
        },
        {
          "i": 5,
          "c": "や",
          "t": 40213
        },
        {
          "i": 6,
          "c": "言",
          "t": 40419
        },
        {
          "i": 7,
          "c": "葉",
          "t": 40588
        },
        {
          "i": 8,
          "c": "が",
          "t": 40888
        }
      ]
    },
    {
      "index": 8,
      "text": "君は好きなのかなって",
      "startTimeMs": 41904,
      "endTimeMs": 43990,
      "chars": [
        {
          "i": 0,
          "c": "君",
          "t": 41904
        },
        {
          "i": 1,
          "c": "は",
          "t": 42285
        },
        {
          "i": 2,
          "c": "好",
          "t": 42443
        },
        {
          "i": 3,
          "c": "き",
          "t": 42677
        },
        {
          "i": 4,
          "c": "な",
          "t": 42983
        },
        {
          "i": 5,
          "c": "の",
          "t": 43156
        },
        {
          "i": 6,
          "c": "か",
          "t": 43328
        },
        {
          "i": 7,
          "c": "な",
          "t": 43493
        },
        {
          "i": 8,
          "c": "っ",
          "t": 43687
        },
        {
          "i": 9,
          "c": "て",
          "t": 43990
        }
      ]
    },
    {
      "index": 9,
      "text": "悩んでる日々それが楽しい",
      "startTimeMs": 44648,
      "endTimeMs": 49258,
      "chars": [
        {
          "i": 0,
          "c": "悩",
          "t": 44648
        },
        {
          "i": 1,
          "c": "ん",
          "t": 44995
        },
        {
          "i": 2,
          "c": "で",
          "t": 45345
        },
        {
          "i": 3,
          "c": "る",
          "t": 45977
        },
        {
          "i": 4,
          "c": "日",
          "t": 46112
        },
        {
          "i": 5,
          "c": "々",
          "t": 46567
        },
        {
          "i": 6,
          "c": "そ",
          "t": 46734
        },
        {
          "i": 7,
          "c": "れ",
          "t": 47071
        },
        {
          "i": 8,
          "c": "が",
          "t": 47401
        },
        {
          "i": 9,
          "c": "楽",
          "t": 47938
        },
        {
          "i": 10,
          "c": "し",
          "t": 48139
        },
        {
          "i": 11,
          "c": "い",
          "t": 49258
        }
      ]
    },
    {
      "index": 10,
      "text": "もらった愛なら100倍で返す",
      "startTimeMs": 49505,
      "endTimeMs": 54547,
      "chars": [
        {
          "i": 0,
          "c": "も",
          "t": 49505
        },
        {
          "i": 1,
          "c": "ら",
          "t": 49678
        },
        {
          "i": 2,
          "c": "っ",
          "t": 49919
        },
        {
          "i": 3,
          "c": "た",
          "t": 50462
        },
        {
          "i": 4,
          "c": "愛",
          "t": 50680
        },
        {
          "i": 5,
          "c": "な",
          "t": 51231
        },
        {
          "i": 6,
          "c": "ら",
          "t": 51399
        },
        {
          "i": 7,
          "c": "1",
          "t": 51991
        },
        {
          "i": 8,
          "c": "0",
          "t": 52165
        },
        {
          "i": 9,
          "c": "0",
          "t": 52595
        },
        {
          "i": 10,
          "c": "倍",
          "t": 52770
        },
        {
          "i": 11,
          "c": "で",
          "t": 53560
        },
        {
          "i": 12,
          "c": "返",
          "t": 53754
        },
        {
          "i": 13,
          "c": "す",
          "t": 54547
        }
      ]
    },
    {
      "index": 11,
      "text": "感じた声援負けられないから",
      "startTimeMs": 55263,
      "endTimeMs": 62461,
      "chars": [
        {
          "i": 0,
          "c": "感",
          "t": 55263
        },
        {
          "i": 1,
          "c": "じ",
          "t": 55454
        },
        {
          "i": 2,
          "c": "た",
          "t": 56067
        },
        {
          "i": 3,
          "c": "声",
          "t": 56816
        },
        {
          "i": 4,
          "c": "援",
          "t": 57485
        },
        {
          "i": 5,
          "c": "負",
          "t": 57696
        },
        {
          "i": 6,
          "c": "け",
          "t": 58044
        },
        {
          "i": 7,
          "c": "ら",
          "t": 58380
        },
        {
          "i": 8,
          "c": "れ",
          "t": 58695
        },
        {
          "i": 9,
          "c": "な",
          "t": 59067
        },
        {
          "i": 10,
          "c": "い",
          "t": 59731
        },
        {
          "i": 11,
          "c": "か",
          "t": 60433
        },
        {
          "i": 12,
          "c": "ら",
          "t": 62461
        }
      ]
    },
    {
      "index": 12,
      "text": "いちばんになりたい",
      "startTimeMs": 62803,
      "endTimeMs": 65208,
      "chars": [
        {
          "i": 0,
          "c": "い",
          "t": 62803
        },
        {
          "i": 1,
          "c": "ち",
          "t": 63201
        },
        {
          "i": 2,
          "c": "ば",
          "t": 63482
        },
        {
          "i": 3,
          "c": "ん",
          "t": 63625
        },
        {
          "i": 4,
          "c": "に",
          "t": 63801
        },
        {
          "i": 5,
          "c": "な",
          "t": 63981
        },
        {
          "i": 6,
          "c": "り",
          "t": 64244
        },
        {
          "i": 7,
          "c": "た",
          "t": 64540
        },
        {
          "i": 8,
          "c": "い",
          "t": 65208
        }
      ]
    },
    {
      "index": 13,
      "text": "まだ小さなヒカリ",
      "startTimeMs": 65555,
      "endTimeMs": 67996,
      "chars": [
        {
          "i": 0,
          "c": "ま",
          "t": 65555
        },
        {
          "i": 1,
          "c": "だ",
          "t": 65913
        },
        {
          "i": 2,
          "c": "小",
          "t": 66254
        },
        {
          "i": 3,
          "c": "さ",
          "t": 66420
        },
        {
          "i": 4,
          "c": "な",
          "t": 66606
        },
        {
          "i": 5,
          "c": "ヒ",
          "t": 66942
        },
        {
          "i": 6,
          "c": "カ",
          "t": 67280
        },
        {
          "i": 7,
          "c": "リ",
          "t": 67996
        }
      ]
    },
    {
      "index": 14,
      "text": "こんな僕だけど",
      "startTimeMs": 68127,
      "endTimeMs": 70712,
      "chars": [
        {
          "i": 0,
          "c": "こ",
          "t": 68127
        },
        {
          "i": 1,
          "c": "ん",
          "t": 68308
        },
        {
          "i": 2,
          "c": "な",
          "t": 68653
        },
        {
          "i": 3,
          "c": "僕",
          "t": 69301
        },
        {
          "i": 4,
          "c": "だ",
          "t": 69634
        },
        {
          "i": 5,
          "c": "け",
          "t": 70019
        },
        {
          "i": 6,
          "c": "ど",
          "t": 70712
        }
      ]
    },
    {
      "index": 15,
      "text": "愛してほしいのです",
      "startTimeMs": 70996,
      "endTimeMs": 74080,
      "chars": [
        {
          "i": 0,
          "c": "愛",
          "t": 70996
        },
        {
          "i": 1,
          "c": "し",
          "t": 71189
        },
        {
          "i": 2,
          "c": "て",
          "t": 71768
        },
        {
          "i": 3,
          "c": "ほ",
          "t": 72093
        },
        {
          "i": 4,
          "c": "し",
          "t": 72401
        },
        {
          "i": 5,
          "c": "い",
          "t": 72712
        },
        {
          "i": 6,
          "c": "の",
          "t": 73225
        },
        {
          "i": 7,
          "c": "で",
          "t": 73401
        },
        {
          "i": 8,
          "c": "す",
          "t": 74080
        }
      ]
    },
    {
      "index": 16,
      "text": "これからもずっと",
      "startTimeMs": 74264,
      "endTimeMs": 76131,
      "chars": [
        {
          "i": 0,
          "c": "こ",
          "t": 74264
        },
        {
          "i": 1,
          "c": "れ",
          "t": 74461
        },
        {
          "i": 2,
          "c": "か",
          "t": 74646
        },
        {
          "i": 3,
          "c": "ら",
          "t": 74846
        },
        {
          "i": 4,
          "c": "も",
          "t": 75161
        },
        {
          "i": 5,
          "c": "ず",
          "t": 75508
        },
        {
          "i": 6,
          "c": "っ",
          "t": 75643
        },
        {
          "i": 7,
          "c": "と",
          "t": 76131
        }
      ]
    },
    {
      "index": 17,
      "text": "一緒に歩いてね",
      "startTimeMs": 76376,
      "endTimeMs": 78927,
      "chars": [
        {
          "i": 0,
          "c": "一",
          "t": 76376
        },
        {
          "i": 1,
          "c": "緒",
          "t": 77134
        },
        {
          "i": 2,
          "c": "に",
          "t": 77339
        },
        {
          "i": 3,
          "c": "歩",
          "t": 77756
        },
        {
          "i": 4,
          "c": "い",
          "t": 77988
        },
        {
          "i": 5,
          "c": "て",
          "t": 78281
        },
        {
          "i": 6,
          "c": "ね",
          "t": 78927
        }
      ]
    },
    {
      "index": 18,
      "text": "愛に溢れてる未来図",
      "startTimeMs": 79246,
      "endTimeMs": 82327,
      "chars": [
        {
          "i": 0,
          "c": "愛",
          "t": 79246
        },
        {
          "i": 1,
          "c": "に",
          "t": 79619
        },
        {
          "i": 2,
          "c": "溢",
          "t": 80252
        },
        {
          "i": 3,
          "c": "れ",
          "t": 80597
        },
        {
          "i": 4,
          "c": "て",
          "t": 80959
        },
        {
          "i": 5,
          "c": "る",
          "t": 81659
        },
        {
          "i": 6,
          "c": "未",
          "t": 81993
        },
        {
          "i": 7,
          "c": "来",
          "t": 82163
        },
        {
          "i": 8,
          "c": "図",
          "t": 82327
        }
      ]
    },
    {
      "index": 19,
      "text": "描いていこう",
      "startTimeMs": 84031,
      "endTimeMs": 95989,
      "chars": [
        {
          "i": 0,
          "c": "描",
          "t": 84031
        },
        {
          "i": 1,
          "c": "い",
          "t": 84399
        },
        {
          "i": 2,
          "c": "て",
          "t": 84732
        },
        {
          "i": 3,
          "c": "い",
          "t": 84906
        },
        {
          "i": 4,
          "c": "こ",
          "t": 85125
        },
        {
          "i": 5,
          "c": "う",
          "t": 95989
        }
      ]
    },
    {
      "index": 20,
      "text": "あざとくするのは当然",
      "startTimeMs": 96425,
      "endTimeMs": 99092,
      "chars": [
        {
          "i": 0,
          "c": "あ",
          "t": 96425
        },
        {
          "i": 1,
          "c": "ざ",
          "t": 96701
        },
        {
          "i": 2,
          "c": "と",
          "t": 96909
        },
        {
          "i": 3,
          "c": "く",
          "t": 97126
        },
        {
          "i": 4,
          "c": "す",
          "t": 97335
        },
        {
          "i": 5,
          "c": "る",
          "t": 97663
        },
        {
          "i": 6,
          "c": "の",
          "t": 97846
        },
        {
          "i": 7,
          "c": "は",
          "t": 98017
        },
        {
          "i": 8,
          "c": "当",
          "t": 98429
        },
        {
          "i": 9,
          "c": "然",
          "t": 99092
        }
      ]
    },
    {
      "index": 21,
      "text": "僕の可愛いところ",
      "startTimeMs": 99458,
      "endTimeMs": 101276,
      "chars": [
        {
          "i": 0,
          "c": "僕",
          "t": 99458
        },
        {
          "i": 1,
          "c": "の",
          "t": 99814
        },
        {
          "i": 2,
          "c": "可",
          "t": 99978
        },
        {
          "i": 3,
          "c": "愛",
          "t": 100309
        },
        {
          "i": 4,
          "c": "い",
          "t": 100487
        },
        {
          "i": 5,
          "c": "と",
          "t": 100825
        },
        {
          "i": 6,
          "c": "こ",
          "t": 100988
        },
        {
          "i": 7,
          "c": "ろ",
          "t": 101276
        }
      ]
    },
    {
      "index": 22,
      "text": "もっとたくさん知ってほしいから",
      "startTimeMs": 101944,
      "endTimeMs": 107319,
      "chars": [
        {
          "i": 0,
          "c": "も",
          "t": 101944
        },
        {
          "i": 1,
          "c": "っ",
          "t": 102119
        },
        {
          "i": 2,
          "c": "と",
          "t": 102612
        },
        {
          "i": 3,
          "c": "た",
          "t": 102951
        },
        {
          "i": 4,
          "c": "く",
          "t": 103275
        },
        {
          "i": 5,
          "c": "さ",
          "t": 103632
        },
        {
          "i": 6,
          "c": "ん",
          "t": 103968
        },
        {
          "i": 7,
          "c": "知",
          "t": 104453
        },
        {
          "i": 8,
          "c": "っ",
          "t": 104650
        },
        {
          "i": 9,
          "c": "て",
          "t": 104981
        },
        {
          "i": 10,
          "c": "ほ",
          "t": 105297
        },
        {
          "i": 11,
          "c": "し",
          "t": 105485
        },
        {
          "i": 12,
          "c": "い",
          "t": 105673
        },
        {
          "i": 13,
          "c": "か",
          "t": 105841
        },
        {
          "i": 14,
          "c": "ら",
          "t": 107319
        }
      ]
    },
    {
      "index": 23,
      "text": "二番じゃ嫉妬しちゃうな",
      "startTimeMs": 107480,
      "endTimeMs": 110084,
      "chars": [
        {
          "i": 0,
          "c": "二",
          "t": 107480
        },
        {
          "i": 1,
          "c": "番",
          "t": 107955
        },
        {
          "i": 2,
          "c": "じ",
          "t": 108117
        },
        {
          "i": 3,
          "c": "ゃ",
          "t": 108420
        },
        {
          "i": 4,
          "c": "嫉",
          "t": 108788
        },
        {
          "i": 5,
          "c": "妬",
          "t": 109010
        },
        {
          "i": 6,
          "c": "し",
          "t": 109181
        },
        {
          "i": 7,
          "c": "ち",
          "t": 109336
        },
        {
          "i": 8,
          "c": "ゃ",
          "t": 109507
        },
        {
          "i": 9,
          "c": "う",
          "t": 109648
        },
        {
          "i": 10,
          "c": "な",
          "t": 110084
        }
      ]
    },
    {
      "index": 24,
      "text": "一番がやっぱりいいな",
      "startTimeMs": 110459,
      "endTimeMs": 112374,
      "chars": [
        {
          "i": 0,
          "c": "一",
          "t": 110459
        },
        {
          "i": 1,
          "c": "番",
          "t": 110797
        },
        {
          "i": 2,
          "c": "が",
          "t": 110961
        },
        {
          "i": 3,
          "c": "や",
          "t": 111316
        },
        {
          "i": 4,
          "c": "っ",
          "t": 111460
        },
        {
          "i": 5,
          "c": "ぱ",
          "t": 111647
        },
        {
          "i": 6,
          "c": "り",
          "t": 111818
        },
        {
          "i": 7,
          "c": "い",
          "t": 112003
        },
        {
          "i": 8,
          "c": "い",
          "t": 112178
        },
        {
          "i": 9,
          "c": "な",
          "t": 112374
        }
      ]
    },
    {
      "index": 25,
      "text": "勇気を出して踏み出すんだ",
      "startTimeMs": 112595,
      "endTimeMs": 118011,
      "chars": [
        {
          "i": 0,
          "c": "勇",
          "t": 112595
        },
        {
          "i": 1,
          "c": "気",
          "t": 113502
        },
        {
          "i": 2,
          "c": "を",
          "t": 113885
        },
        {
          "i": 3,
          "c": "出",
          "t": 114189
        },
        {
          "i": 4,
          "c": "し",
          "t": 114514
        },
        {
          "i": 5,
          "c": "て",
          "t": 115125
        },
        {
          "i": 6,
          "c": "踏",
          "t": 115436
        },
        {
          "i": 7,
          "c": "み",
          "t": 115698
        },
        {
          "i": 8,
          "c": "出",
          "t": 115984
        },
        {
          "i": 9,
          "c": "す",
          "t": 116323
        },
        {
          "i": 10,
          "c": "ん",
          "t": 116636
        },
        {
          "i": 11,
          "c": "だ",
          "t": 118011
        }
      ]
    },
    {
      "index": 26,
      "text": "一緒に見た夢叶えてみせるよ",
      "startTimeMs": 118375,
      "endTimeMs": 123470,
      "chars": [
        {
          "i": 0,
          "c": "一",
          "t": 118375
        },
        {
          "i": 1,
          "c": "緒",
          "t": 118913
        },
        {
          "i": 2,
          "c": "に",
          "t": 119210
        },
        {
          "i": 3,
          "c": "見",
          "t": 119366
        },
        {
          "i": 4,
          "c": "た",
          "t": 119859
        },
        {
          "i": 5,
          "c": "夢",
          "t": 120569
        },
        {
          "i": 6,
          "c": "叶",
          "t": 121247
        },
        {
          "i": 7,
          "c": "え",
          "t": 121409
        },
        {
          "i": 8,
          "c": "て",
          "t": 121999
        },
        {
          "i": 9,
          "c": "み",
          "t": 122195
        },
        {
          "i": 10,
          "c": "せ",
          "t": 122612
        },
        {
          "i": 11,
          "c": "る",
          "t": 122809
        },
        {
          "i": 12,
          "c": "よ",
          "t": 123470
        }
      ]
    },
    {
      "index": 27,
      "text": "想いを重ねて負けたくないから",
      "startTimeMs": 123626,
      "endTimeMs": 130389,
      "chars": [
        {
          "i": 0,
          "c": "想",
          "t": 123626
        },
        {
          "i": 1,
          "c": "い",
          "t": 124281
        },
        {
          "i": 2,
          "c": "を",
          "t": 124709
        },
        {
          "i": 3,
          "c": "重",
          "t": 124889
        },
        {
          "i": 4,
          "c": "ね",
          "t": 125444
        },
        {
          "i": 5,
          "c": "て",
          "t": 126065
        },
        {
          "i": 6,
          "c": "負",
          "t": 126246
        },
        {
          "i": 7,
          "c": "け",
          "t": 126594
        },
        {
          "i": 8,
          "c": "た",
          "t": 126927
        },
        {
          "i": 9,
          "c": "く",
          "t": 127262
        },
        {
          "i": 10,
          "c": "な",
          "t": 127624
        },
        {
          "i": 11,
          "c": "い",
          "t": 128287
        },
        {
          "i": 12,
          "c": "か",
          "t": 128929
        },
        {
          "i": 13,
          "c": "ら",
          "t": 130389
        }
      ]
    },
    {
      "index": 28,
      "text": "せーのでほらジャンプ!",
      "startTimeMs": 131923,
      "endTimeMs": 133892,
      "chars": [
        {
          "i": 0,
          "c": "せ",
          "t": 131923
        },
        {
          "i": 1,
          "c": "ー",
          "t": 132116
        },
        {
          "i": 2,
          "c": "の",
          "t": 132446
        },
        {
          "i": 3,
          "c": "で",
          "t": 132630
        },
        {
          "i": 4,
          "c": "ほ",
          "t": 132828
        },
        {
          "i": 5,
          "c": "ら",
          "t": 132994
        },
        {
          "i": 6,
          "c": "ジ",
          "t": 133148
        },
        {
          "i": 7,
          "c": "ャ",
          "t": 133297
        },
        {
          "i": 8,
          "c": "ン",
          "t": 133460
        },
        {
          "i": 9,
          "c": "プ",
          "t": 133624
        },
        {
          "i": 10,
          "c": "!",
          "t": 133892
        }
      ]
    },
    {
      "index": 29,
      "text": "いちばんになりたい",
      "startTimeMs": 134179,
      "endTimeMs": 136543,
      "chars": [
        {
          "i": 0,
          "c": "い",
          "t": 134179
        },
        {
          "i": 1,
          "c": "ち",
          "t": 134502
        },
        {
          "i": 2,
          "c": "ば",
          "t": 134664
        },
        {
          "i": 3,
          "c": "ん",
          "t": 134840
        },
        {
          "i": 4,
          "c": "に",
          "t": 135014
        },
        {
          "i": 5,
          "c": "な",
          "t": 135192
        },
        {
          "i": 6,
          "c": "り",
          "t": 135504
        },
        {
          "i": 7,
          "c": "た",
          "t": 135839
        },
        {
          "i": 8,
          "c": "い",
          "t": 136543
        }
      ]
    },
    {
      "index": 30,
      "text": "ここから一歩ずつ",
      "startTimeMs": 136700,
      "endTimeMs": 139214,
      "chars": [
        {
          "i": 0,
          "c": "こ",
          "t": 136700
        },
        {
          "i": 1,
          "c": "こ",
          "t": 137191
        },
        {
          "i": 2,
          "c": "か",
          "t": 137390
        },
        {
          "i": 3,
          "c": "ら",
          "t": 137600
        },
        {
          "i": 4,
          "c": "一",
          "t": 138089
        },
        {
          "i": 5,
          "c": "歩",
          "t": 138334
        },
        {
          "i": 6,
          "c": "ず",
          "t": 138639
        },
        {
          "i": 7,
          "c": "つ",
          "t": 139214
        }
      ]
    },
    {
      "index": 31,
      "text": "まだまだ進化中",
      "startTimeMs": 139399,
      "endTimeMs": 141924,
      "chars": [
        {
          "i": 0,
          "c": "ま",
          "t": 139399
        },
        {
          "i": 1,
          "c": "だ",
          "t": 139582
        },
        {
          "i": 2,
          "c": "ま",
          "t": 139762
        },
        {
          "i": 3,
          "c": "だ",
          "t": 139963
        },
        {
          "i": 4,
          "c": "進",
          "t": 140394
        },
        {
          "i": 5,
          "c": "化",
          "t": 141035
        },
        {
          "i": 6,
          "c": "中",
          "t": 141924
        }
      ]
    },
    {
      "index": 32,
      "text": "目を離さないでいて",
      "startTimeMs": 142275,
      "endTimeMs": 145337,
      "chars": [
        {
          "i": 0,
          "c": "目",
          "t": 142275
        },
        {
          "i": 1,
          "c": "を",
          "t": 142443
        },
        {
          "i": 2,
          "c": "離",
          "t": 142726
        },
        {
          "i": 3,
          "c": "さ",
          "t": 143268
        },
        {
          "i": 4,
          "c": "な",
          "t": 143487
        },
        {
          "i": 5,
          "c": "い",
          "t": 143708
        },
        {
          "i": 6,
          "c": "で",
          "t": 144045
        },
        {
          "i": 7,
          "c": "い",
          "t": 144641
        },
        {
          "i": 8,
          "c": "て",
          "t": 145337
        }
      ]
    },
    {
      "index": 33,
      "text": "照れ隠しだって",
      "startTimeMs": 145651,
      "endTimeMs": 147469,
      "chars": [
        {
          "i": 0,
          "c": "照",
          "t": 145651
        },
        {
          "i": 1,
          "c": "れ",
          "t": 145818
        },
        {
          "i": 2,
          "c": "隠",
          "t": 145999
        },
        {
          "i": 3,
          "c": "し",
          "t": 146177
        },
        {
          "i": 4,
          "c": "だ",
          "t": 146449
        },
        {
          "i": 5,
          "c": "っ",
          "t": 146616
        },
        {
          "i": 6,
          "c": "て",
          "t": 147469
        }
      ]
    },
    {
      "index": 34,
      "text": "言い訳しちゃうぐらい",
      "startTimeMs": 147778,
      "endTimeMs": 150245,
      "chars": [
        {
          "i": 0,
          "c": "言",
          "t": 147778
        },
        {
          "i": 1,
          "c": "い",
          "t": 147907
        },
        {
          "i": 2,
          "c": "訳",
          "t": 148559
        },
        {
          "i": 3,
          "c": "し",
          "t": 148742
        },
        {
          "i": 4,
          "c": "ち",
          "t": 148922
        },
        {
          "i": 5,
          "c": "ゃ",
          "t": 149231
        },
        {
          "i": 6,
          "c": "う",
          "t": 149566
        },
        {
          "i": 7,
          "c": "ぐ",
          "t": 149738
        },
        {
          "i": 8,
          "c": "ら",
          "t": 149954
        },
        {
          "i": 9,
          "c": "い",
          "t": 150245
        }
      ]
    },
    {
      "index": 35,
      "text": "真っすぐな想い",
      "startTimeMs": 150606,
      "endTimeMs": 152948,
      "chars": [
        {
          "i": 0,
          "c": "真",
          "t": 150606
        },
        {
          "i": 1,
          "c": "っ",
          "t": 150776
        },
        {
          "i": 2,
          "c": "す",
          "t": 150958
        },
        {
          "i": 3,
          "c": "ぐ",
          "t": 151128
        },
        {
          "i": 4,
          "c": "な",
          "t": 151586
        },
        {
          "i": 5,
          "c": "想",
          "t": 152250
        },
        {
          "i": 6,
          "c": "い",
          "t": 152948
        }
      ]
    },
    {
      "index": 36,
      "text": "笑顔で届けにいく",
      "startTimeMs": 153236,
      "endTimeMs": 156458,
      "chars": [
        {
          "i": 0,
          "c": "笑",
          "t": 153236
        },
        {
          "i": 1,
          "c": "顔",
          "t": 153476
        },
        {
          "i": 2,
          "c": "で",
          "t": 154738
        },
        {
          "i": 3,
          "c": "届",
          "t": 155234
        },
        {
          "i": 4,
          "c": "け",
          "t": 155652
        },
        {
          "i": 5,
          "c": "に",
          "t": 155997
        },
        {
          "i": 6,
          "c": "い",
          "t": 156297
        },
        {
          "i": 7,
          "c": "く",
          "t": 156458
        }
      ]
    },
    {
      "index": 37,
      "text": "もっと!いくよ!",
      "startTimeMs": 156631,
      "endTimeMs": 157839,
      "chars": [
        {
          "i": 0,
          "c": "も",
          "t": 156631
        },
        {
          "i": 1,
          "c": "っ",
          "t": 156804
        },
        {
          "i": 2,
          "c": "と",
          "t": 156976
        },
        {
          "i": 3,
          "c": "!",
          "t": 157154
        },
        {
          "i": 4,
          "c": "い",
          "t": 157321
        },
        {
          "i": 5,
          "c": "く",
          "t": 157496
        },
        {
          "i": 6,
          "c": "よ",
          "t": 157662
        },
        {
          "i": 7,
          "c": "!",
          "t": 157839
        }
      ]
    },
    {
      "index": 38,
      "text": "まだまだ!Go Go!",
      "startTimeMs": 157978,
      "endTimeMs": 159603,
      "chars": [
        {
          "i": 0,
          "c": "ま",
          "t": 157978
        },
        {
          "i": 1,
          "c": "だ",
          "t": 158158
        },
        {
          "i": 2,
          "c": "ま",
          "t": 158331
        },
        {
          "i": 3,
          "c": "だ",
          "t": 158830
        },
        {
          "i": 4,
          "c": "!",
          "t": 158942
        },
        {
          "i": 5,
          "c": "G",
          "t": 159043
        },
        {
          "i": 6,
          "c": "o",
          "t": 159139
        },
        {
          "i": 7,
          "c": " ",
          "t": 159243
        },
        {
          "i": 8,
          "c": "G",
          "t": 159355
        },
        {
          "i": 9,
          "c": "o",
          "t": 159482
        },
        {
          "i": 10,
          "c": "!",
          "t": 159603
        }
      ]
    },
    {
      "index": 39,
      "text": "もっと!いくよ!",
      "startTimeMs": 159727,
      "endTimeMs": 160638,
      "chars": [
        {
          "i": 0,
          "c": "も",
          "t": 159727
        },
        {
          "i": 1,
          "c": "っ",
          "t": 159860
        },
        {
          "i": 2,
          "c": "と",
          "t": 159989
        },
        {
          "i": 3,
          "c": "!",
          "t": 160110
        },
        {
          "i": 4,
          "c": "い",
          "t": 160213
        },
        {
          "i": 5,
          "c": "く",
          "t": 160355
        },
        {
          "i": 6,
          "c": "よ",
          "t": 160508
        },
        {
          "i": 7,
          "c": "!",
          "t": 160638
        }
      ]
    },
    {
      "index": 40,
      "text": "まだまだ!Jumpin' !",
      "startTimeMs": 160856,
      "endTimeMs": 162608,
      "chars": [
        {
          "i": 0,
          "c": "ま",
          "t": 160856
        },
        {
          "i": 1,
          "c": "だ",
          "t": 161112
        },
        {
          "i": 2,
          "c": "ま",
          "t": 161158
        },
        {
          "i": 3,
          "c": "だ",
          "t": 161187
        },
        {
          "i": 4,
          "c": "!",
          "t": 161234
        },
        {
          "i": 5,
          "c": "J",
          "t": 161279
        },
        {
          "i": 6,
          "c": "u",
          "t": 161324
        },
        {
          "i": 7,
          "c": "m",
          "t": 161355
        },
        {
          "i": 8,
          "c": "p",
          "t": 161527
        },
        {
          "i": 9,
          "c": "i",
          "t": 161679
        },
        {
          "i": 10,
          "c": "n",
          "t": 161846
        },
        {
          "i": 11,
          "c": "'",
          "t": 162027
        },
        {
          "i": 12,
          "c": " ",
          "t": 162465
        },
        {
          "i": 13,
          "c": "!",
          "t": 162608
        }
      ]
    },
    {
      "index": 41,
      "text": "せーの!Yeah!",
      "startTimeMs": 162777,
      "endTimeMs": 177603,
      "chars": [
        {
          "i": 0,
          "c": "せ",
          "t": 162777
        },
        {
          "i": 1,
          "c": "ー",
          "t": 162946
        },
        {
          "i": 2,
          "c": "の",
          "t": 163148
        },
        {
          "i": 3,
          "c": "!",
          "t": 163349
        },
        {
          "i": 4,
          "c": "Y",
          "t": 163533
        },
        {
          "i": 5,
          "c": "e",
          "t": 163697
        },
        {
          "i": 6,
          "c": "a",
          "t": 163848
        },
        {
          "i": 7,
          "c": "h",
          "t": 164145
        },
        {
          "i": 8,
          "c": "!",
          "t": 177603
        }
      ]
    },
    {
      "index": 42,
      "text": "ずっと自信が持てなかった",
      "startTimeMs": 178332,
      "endTimeMs": 183509,
      "chars": [
        {
          "i": 0,
          "c": "ず",
          "t": 178332
        },
        {
          "i": 1,
          "c": "っ",
          "t": 178475
        },
        {
          "i": 2,
          "c": "と",
          "t": 178968
        },
        {
          "i": 3,
          "c": "自",
          "t": 179128
        },
        {
          "i": 4,
          "c": "信",
          "t": 179633
        },
        {
          "i": 5,
          "c": "が",
          "t": 180844
        },
        {
          "i": 6,
          "c": "持",
          "t": 181033
        },
        {
          "i": 7,
          "c": "て",
          "t": 181437
        },
        {
          "i": 8,
          "c": "な",
          "t": 181607
        },
        {
          "i": 9,
          "c": "か",
          "t": 181866
        },
        {
          "i": 10,
          "c": "っ",
          "t": 182403
        },
        {
          "i": 11,
          "c": "た",
          "t": 183509
        }
      ]
    },
    {
      "index": 43,
      "text": "僕のことを変えてくれた君へ",
      "startTimeMs": 183674,
      "endTimeMs": 189043,
      "chars": [
        {
          "i": 0,
          "c": "僕",
          "t": 183674
        },
        {
          "i": 1,
          "c": "の",
          "t": 184267
        },
        {
          "i": 2,
          "c": "こ",
          "t": 184435
        },
        {
          "i": 3,
          "c": "と",
          "t": 184951
        },
        {
          "i": 4,
          "c": "を",
          "t": 185120
        },
        {
          "i": 5,
          "c": "変",
          "t": 185627
        },
        {
          "i": 6,
          "c": "え",
          "t": 185899
        },
        {
          "i": 7,
          "c": "て",
          "t": 186370
        },
        {
          "i": 8,
          "c": "く",
          "t": 186621
        },
        {
          "i": 9,
          "c": "れ",
          "t": 186961
        },
        {
          "i": 10,
          "c": "た",
          "t": 187393
        },
        {
          "i": 11,
          "c": "君",
          "t": 187927
        },
        {
          "i": 12,
          "c": "へ",
          "t": 189043
        }
      ]
    },
    {
      "index": 44,
      "text": "胸を張って今なら言える",
      "startTimeMs": 189190,
      "endTimeMs": 194416,
      "chars": [
        {
          "i": 0,
          "c": "胸",
          "t": 189190
        },
        {
          "i": 1,
          "c": "を",
          "t": 189889
        },
        {
          "i": 2,
          "c": "張",
          "t": 190309
        },
        {
          "i": 3,
          "c": "っ",
          "t": 190645
        },
        {
          "i": 4,
          "c": "て",
          "t": 191683
        },
        {
          "i": 5,
          "c": "今",
          "t": 191862
        },
        {
          "i": 6,
          "c": "な",
          "t": 192112
        },
        {
          "i": 7,
          "c": "ら",
          "t": 192773
        },
        {
          "i": 8,
          "c": "言",
          "t": 193152
        },
        {
          "i": 9,
          "c": "え",
          "t": 193315
        },
        {
          "i": 10,
          "c": "る",
          "t": 194416
        }
      ]
    },
    {
      "index": 45,
      "text": "出会ってくれて本当にありがとう",
      "startTimeMs": 194594,
      "endTimeMs": 202314,
      "chars": [
        {
          "i": 0,
          "c": "出",
          "t": 194594
        },
        {
          "i": 1,
          "c": "会",
          "t": 194908
        },
        {
          "i": 2,
          "c": "っ",
          "t": 195216
        },
        {
          "i": 3,
          "c": "て",
          "t": 195436
        },
        {
          "i": 4,
          "c": "く",
          "t": 195833
        },
        {
          "i": 5,
          "c": "れ",
          "t": 196001
        },
        {
          "i": 6,
          "c": "て",
          "t": 196824
        },
        {
          "i": 7,
          "c": "本",
          "t": 197496
        },
        {
          "i": 8,
          "c": "当",
          "t": 198134
        },
        {
          "i": 9,
          "c": "に",
          "t": 198761
        },
        {
          "i": 10,
          "c": "あ",
          "t": 199227
        },
        {
          "i": 11,
          "c": "り",
          "t": 199889
        },
        {
          "i": 12,
          "c": "が",
          "t": 200552
        },
        {
          "i": 13,
          "c": "と",
          "t": 200702
        },
        {
          "i": 14,
          "c": "う",
          "t": 202314
        }
      ]
    },
    {
      "index": 46,
      "text": "いちばんになるから",
      "startTimeMs": 202667,
      "endTimeMs": 205073,
      "chars": [
        {
          "i": 0,
          "c": "い",
          "t": 202667
        },
        {
          "i": 1,
          "c": "ち",
          "t": 203082
        },
        {
          "i": 2,
          "c": "ば",
          "t": 203238
        },
        {
          "i": 3,
          "c": "ん",
          "t": 203462
        },
        {
          "i": 4,
          "c": "に",
          "t": 203612
        },
        {
          "i": 5,
          "c": "な",
          "t": 203769
        },
        {
          "i": 6,
          "c": "る",
          "t": 204074
        },
        {
          "i": 7,
          "c": "か",
          "t": 204411
        },
        {
          "i": 8,
          "c": "ら",
          "t": 205073
        }
      ]
    },
    {
      "index": 47,
      "text": "もっと大きなヒカリ",
      "startTimeMs": 205201,
      "endTimeMs": 207880,
      "chars": [
        {
          "i": 0,
          "c": "も",
          "t": 205201
        },
        {
          "i": 1,
          "c": "っ",
          "t": 205417
        },
        {
          "i": 2,
          "c": "と",
          "t": 205799
        },
        {
          "i": 3,
          "c": "大",
          "t": 206149
        },
        {
          "i": 4,
          "c": "き",
          "t": 206298
        },
        {
          "i": 5,
          "c": "な",
          "t": 206459
        },
        {
          "i": 6,
          "c": "ヒ",
          "t": 206846
        },
        {
          "i": 7,
          "c": "カ",
          "t": 207219
        },
        {
          "i": 8,
          "c": "リ",
          "t": 207880
        }
      ]
    },
    {
      "index": 48,
      "text": "どんな僕だって",
      "startTimeMs": 208023,
      "endTimeMs": 210595,
      "chars": [
        {
          "i": 0,
          "c": "ど",
          "t": 208023
        },
        {
          "i": 1,
          "c": "ん",
          "t": 208206
        },
        {
          "i": 2,
          "c": "な",
          "t": 208546
        },
        {
          "i": 3,
          "c": "僕",
          "t": 209176
        },
        {
          "i": 4,
          "c": "だ",
          "t": 209525
        },
        {
          "i": 5,
          "c": "っ",
          "t": 209901
        },
        {
          "i": 6,
          "c": "て",
          "t": 210595
        }
      ]
    },
    {
      "index": 49,
      "text": "愛してほしいのです",
      "startTimeMs": 210934,
      "endTimeMs": 213996,
      "chars": [
        {
          "i": 0,
          "c": "愛",
          "t": 210934
        },
        {
          "i": 1,
          "c": "し",
          "t": 211298
        },
        {
          "i": 2,
          "c": "て",
          "t": 211635
        },
        {
          "i": 3,
          "c": "ほ",
          "t": 211967
        },
        {
          "i": 4,
          "c": "し",
          "t": 212282
        },
        {
          "i": 5,
          "c": "い",
          "t": 212662
        },
        {
          "i": 6,
          "c": "の",
          "t": 213174
        },
        {
          "i": 7,
          "c": "で",
          "t": 213312
        },
        {
          "i": 8,
          "c": "す",
          "t": 213996
        }
      ]
    },
    {
      "index": 50,
      "text": "まだまだ足りない",
      "startTimeMs": 214141,
      "endTimeMs": 216020,
      "chars": [
        {
          "i": 0,
          "c": "ま",
          "t": 214141
        },
        {
          "i": 1,
          "c": "だ",
          "t": 214299
        },
        {
          "i": 2,
          "c": "ま",
          "t": 214448
        },
        {
          "i": 3,
          "c": "だ",
          "t": 214667
        },
        {
          "i": 4,
          "c": "足",
          "t": 214981
        },
        {
          "i": 5,
          "c": "り",
          "t": 215346
        },
        {
          "i": 6,
          "c": "な",
          "t": 215491
        },
        {
          "i": 7,
          "c": "い",
          "t": 216020
        }
      ]
    },
    {
      "index": 51,
      "text": "もっと欲張っていい?",
      "startTimeMs": 216194,
      "endTimeMs": 218571,
      "chars": [
        {
          "i": 0,
          "c": "も",
          "t": 216194
        },
        {
          "i": 1,
          "c": "っ",
          "t": 216341
        },
        {
          "i": 2,
          "c": "と",
          "t": 216738
        },
        {
          "i": 3,
          "c": "欲",
          "t": 217085
        },
        {
          "i": 4,
          "c": "張",
          "t": 217418
        },
        {
          "i": 5,
          "c": "っ",
          "t": 217777
        },
        {
          "i": 6,
          "c": "て",
          "t": 217931
        },
        {
          "i": 7,
          "c": "い",
          "t": 218081
        },
        {
          "i": 8,
          "c": "い",
          "t": 218238
        },
        {
          "i": 9,
          "c": "?",
          "t": 218571
        }
      ]
    },
    {
      "index": 52,
      "text": "100倍の愛で",
      "startTimeMs": 218962,
      "endTimeMs": 221517,
      "chars": [
        {
          "i": 0,
          "c": "1",
          "t": 218962
        },
        {
          "i": 1,
          "c": "0",
          "t": 219095
        },
        {
          "i": 2,
          "c": "0",
          "t": 219412
        },
        {
          "i": 3,
          "c": "倍",
          "t": 219803
        },
        {
          "i": 4,
          "c": "の",
          "t": 220238
        },
        {
          "i": 5,
          "c": "愛",
          "t": 220852
        },
        {
          "i": 6,
          "c": "で",
          "t": 221517
        }
      ]
    },
    {
      "index": 53,
      "text": "世界が輝いてく",
      "startTimeMs": 221870,
      "endTimeMs": 226219,
      "chars": [
        {
          "i": 0,
          "c": "世",
          "t": 221870
        },
        {
          "i": 1,
          "c": "界",
          "t": 222057
        },
        {
          "i": 2,
          "c": "が",
          "t": 223279
        },
        {
          "i": 3,
          "c": "輝",
          "t": 224030
        },
        {
          "i": 4,
          "c": "い",
          "t": 224537
        },
        {
          "i": 5,
          "c": "て",
          "t": 224927
        },
        {
          "i": 6,
          "c": "く",
          "t": 226219
        }
      ]
    }
  ]
}